gst_calculation/__init__.py
gst_calculation/gst.py
gst_calculation-0.1.2.dist-info/LICENSE
gst_calculation-0.1.2.dist-info/METADATA
gst_calculation-0.1.2.dist-info/WHEEL
gst_calculation-0.1.2.dist-info/top_level.txt
gst_calculation-0.1.2.dist-info/RECORD
