Metadata-Version: 2.1
Name: gst-calculation
Version: 0.1.2
Summary: This package contains Greedy String Tiling calculation
Home-page: https://github.com/tomytw/gst-calculation
Author: Tomy Widjaja
Author-email: tomywid77@gmail.com
License: UNKNOWN
Platform: UNKNOWN
Classifier: Programming Language :: Python :: 3.7
Classifier: License :: OSI Approved :: MIT License
Classifier: Topic :: Scientific/Engineering :: Artificial Intelligence
Classifier: Topic :: Text Processing :: General
Requires-Python: >=3.7
License-File: LICENSE
